<?xml version="1.0" encoding="UTF-8"?>
<copybook name="GSEGIAAA" type="CWS">
  <header>
    <property name="FWO">BUSINESS</property>
    <property name="Length">31000</property>
    <property name="RouterTransaction">FRWK1100</property>
  </header>
  <inputdependencies>
    <dependency>FRWKGL01</dependency>
    <dependency>GSEGGLAA</dependency>
    <dependency>GSEGGLAE</dependency>
  </inputdependencies>
  <input maxBytes="41" />
  <outputdependencies>
    <dependency>FRWKGL01</dependency>
    <dependency>FRWKEBL2</dependency>
    <dependency>FRWKEBL3</dependency>
    <dependency>GSEGGLBB</dependency>
    <dependency>GSEGGLAF</dependency>
  </outputdependencies>
  <output maxBytes="190" />
</copybook>

