<?xml version="1.0" encoding="UTF-8"?>
<copybook name="NPCCWX2E" type="CWS">
  <properties>
    <property name="FWO">BUSINESS</property>
    <property name="rawText">false</property>
  </properties>
  <input maxBytes="3453">
    <register name="NPCCWX2E-HEADER">
      <field name="NPCCWX2E-COD-LAYOUT" pic="X(008)" length="8" bytes="8" usage="DISPLAY" type="ALPHANUM" value="NPCCWX2E" />
      <field name="NPCCWX2E-TAM-LAYOUT" pic="9(005)" length="5" bytes="5" usage="DISPLAY" type="NUMERIC" value="03453" />
    </register>
    <register name="NPCCWX2E-REGISTRO">
      <field name="NPCCWX2E-CBANQR-CMBIO-FNDNG" pic="9(010)" length="10" bytes="10" usage="DISPLAY" type="NUMERIC" />
      <field name="NPCCWX2E-CINDCD-NEGOC-CARTA" pic="X(001)" length="1" bytes="1" usage="DISPLAY" type="ALPHANUM" />
      <field name="NPCCWX2E-VALOR-OPERACAO" pic="9(015)V9(002)" length="17" bytes="17" usage="DISPLAY" type="NUMERIC" decimals="2" />
      <field name="NPCCWX2E-TDIA-FINAN-DSEMB" pic="9(005)" length="5" bytes="5" usage="DISPLAY" type="NUMERIC" />
      <field name="NPCCWX2E-SPREAD-CLEAN" pic="9(003)V9(005)" length="8" bytes="8" usage="DISPLAY" type="NUMERIC" decimals="5" />
      <field name="NPCCWX2E-PTX-FIXA-CMBIO" pic="9(003)V9(005)" length="8" bytes="8" usage="DISPLAY" type="NUMERIC" decimals="5" />
      <field name="NPCCWX2E-VTRAVA-LIBOR-CMBIO" pic="9(003)V9(005)" length="8" bytes="8" usage="DISPLAY" type="NUMERIC" decimals="5" />
      <field name="NPCCWX2E-CINDCD-TIPO-ACCES" pic="9(002)" length="2" bytes="2" usage="DISPLAY" type="NUMERIC" />
      <field name="NPCCWX2E-CPAIS" pic="9(003)" length="3" bytes="3" usage="DISPLAY" type="NUMERIC" />
      <field name="NPCCWX2E-DVALDD-NEGOC-CMBIO" pic="X(010)" length="10" bytes="10" usage="DISPLAY" type="ALPHANUM" />
      <field name="NPCCWX2E-CPRODT-SERVC" pic="9(008)" length="8" bytes="8" usage="DISPLAY" type="NUMERIC" />
      <field name="NPCCWX2E-NBLETO-NEGOC-CMBIO" pic="9(010)" length="10" bytes="10" usage="DISPLAY" type="NUMERIC" />
      <field name="NPCCWX2E-CINDCD-NEGOC-SWAP" pic="X(001)" length="1" bytes="1" usage="DISPLAY" type="ALPHANUM" />
      <field name="NPCCWX2E-CNEGOC-SWAP-FLUXO" pic="X(001)" length="1" bytes="1" usage="DISPLAY" type="ALPHANUM" />
      <field name="NPCCWX2E-CINDCD-ECONM-MOEDA" pic="9(005)" length="5" bytes="5" usage="DISPLAY" type="NUMERIC" />
      <field name="NPCCWX2E-VMIN-COBR-COMIS" pic="9(015)V9(002)" length="17" bytes="17" usage="DISPLAY" type="NUMERIC" decimals="2" />
      <field name="NPCCWX2E-QTD-OCORR" pic="9(003)" length="3" bytes="3" usage="DISPLAY" type="NUMERIC" />
      <field name="NPCCWX2E-QTD-OCORR-MERC" pic="9(003)" length="3" bytes="3" usage="DISPLAY" type="NUMERIC" />
      <register name="NPCCWX2E-LISTA" minOccurs="0" maxOccurs="20" depends="NPCCWX2E-QTD-OCORR" dependsType="number">
        <field name="NPCCWX2E-CINDCD-PCOBR-PRINC" pic="9(002)" length="2" bytes="2" usage="DISPLAY" type="NUMERIC" />
        <field name="NPCCWX2E-VPREVT-DSEMB-CMBIO" pic="9(015)V9(002)" length="17" bytes="17" usage="DISPLAY" type="NUMERIC" decimals="2" />
        <field name="NPCCWX2E-DPREVT-DSEMB-CMBIO" pic="X(010)" length="10" bytes="10" usage="DISPLAY" type="ALPHANUM" />
        <field name="NPCCWX2E-CFLUXO-LIQDC-PRINC" pic="9(002)" length="2" bytes="2" usage="DISPLAY" type="NUMERIC" />
        <field name="NPCCWX2E-CFLUXO-LIQDC-JURO" pic="9(002)" length="2" bytes="2" usage="DISPLAY" type="NUMERIC" />
        <field name="NPCCWX2E-TDIA-CAREN-PRINC" pic="9(005)" length="5" bytes="5" usage="DISPLAY" type="NUMERIC" />
        <field name="NPCCWX2E-TDIA-CAREN-JURO" pic="9(005)" length="5" bytes="5" usage="DISPLAY" type="NUMERIC" />
        <field name="NPCCWX2E-QPCELA-TRADE-PRINC" pic="9(005)" length="5" bytes="5" usage="DISPLAY" type="NUMERIC" />
        <field name="NPCCWX2E-QPCELA-TRADE-JURO" pic="9(005)" length="5" bytes="5" usage="DISPLAY" type="NUMERIC" />
        <field name="NPCCWX2E-CMOMEN-COBR-CMBIO" pic="9(001)" length="1" bytes="1" usage="DISPLAY" type="NUMERIC" />
        <field name="NPCCWX2E-NDSEMB-CMBIO-TRADE" pic="9(005)" length="5" bytes="5" usage="DISPLAY" type="NUMERIC" />
        <field name="NPCCWX2E-VTX-LIBOR-CMBIO" pic="9(003)V9(005)" length="8" bytes="8" usage="DISPLAY" type="NUMERIC" decimals="5" />
        <field name="NPCCWX2E-PTX-JURO-FNDNG" pic="9(003)V9(005)" length="8" bytes="8" usage="DISPLAY" type="NUMERIC" decimals="5" />
        <field name="NPCCWX2E-PJURO-NEGOC-CMBIO" pic="9(003)V9(005)" length="8" bytes="8" usage="DISPLAY" type="NUMERIC" decimals="5" />
        <field name="NPCCWX2E-PSPREAD-TX-CMBIO" pic="9(003)V9(005)" length="8" bytes="8" usage="DISPLAY" type="NUMERIC" decimals="5" />
        <field name="NPCCWX2E-TDIA-FINAN-DSEMB1" pic="9(005)" length="5" bytes="5" usage="DISPLAY" type="NUMERIC" />
        <field name="NPCCWX2E-VJURO-DSEMB-CMBIO" pic="9(015)V9(002)" length="17" bytes="17" usage="DISPLAY" type="NUMERIC" decimals="2" />
        <field name="NPCCWX2E-VDSEMB-NEGOC-CMBIO" pic="9(015)V9(002)" length="17" bytes="17" usage="DISPLAY" type="NUMERIC" decimals="2" />
      </register>
      <register name="NPCCWX2E-LST-MERC" minOccurs="0" maxOccurs="20" depends="NPCCWX2E-QTD-OCORR-MERC" dependsType="number">
        <field name="NPCCWX2E-CMCADO-OPER-CMBIO" pic="9(005)" length="5" bytes="5" usage="DISPLAY" type="NUMERIC" />
        <field name="NPCCWX2E-CUNIC-PSSOA-CMBIO" pic="9(010)" length="10" bytes="10" usage="DISPLAY" type="NUMERIC" />
        <field name="NPCCWX2E-CPAIS-ORIGM" pic="9(003)" length="3" bytes="3" usage="DISPLAY" type="NUMERIC" />
        <field name="NPCCWX2E-CPAIS-BNEFC" pic="9(003)" length="3" bytes="3" usage="DISPLAY" type="NUMERIC" />
        <field name="NPCCWX2E-DPREVT-EMBRQ" pic="X(010)" length="10" bytes="10" usage="DISPLAY" type="ALPHANUM" />
        <field name="NPCCWX2E-NDSEMB-MCADO-TRADE" pic="9(005)" length="5" bytes="5" usage="DISPLAY" type="NUMERIC" />
      </register>
    </register>
  </input>
</copybook>

