<?xml version="1.0" encoding="UTF-8"?>
<copybook name="NPCCWPPE" type="CWS" framework="false">
  <header>
    <property name="FWO">BUSINESS</property>
  </header>
  <input maxBytes="32">
    <register name="NPCCWPPE-HEADER">
      <field name="NPCCWPPE-COD-LAYOUT" pic="X(008)" length="8" bytes="8" usage="DISPLAY" type="ALPHANUM" value="NPCCWPPE" />
      <field name="NPCCWPPE-TAM-LAYOUT" pic="9(005)" length="5" bytes="5" usage="DISPLAY" type="NUMERIC" value="00032" />
    </register>
    <register name="NPCCWPPE-REGISTRO">
      <field name="NPCCWPPE-CUNIC-PSSOA-CMBIO" pic="9(010)" length="10" bytes="10" usage="DISPLAY" type="NUMERIC" />
      <field name="NPCCWPPE-CPRODT-SERVC" pic="9(008)" length="8" bytes="8" usage="DISPLAY" type="NUMERIC" />
      <field name="NPCCWPPE-CIDTFD-MESA-CMBIO" pic="9(001)" length="1" bytes="1" usage="DISPLAY" type="NUMERIC" />
    </register>
  </input>
</copybook>

